{
  "id": "policy_slice",
  "type": "SharedSlice",
  "name": "PolicySlice",
  "description": "PolicySlice",
  "variations": [
    {
      "id": "default",
      "name": "Default",
      "docURL": "...",
      "version": "initial",
      "description": "Default",
      "imageUrl": "",
      "primary": {
        "heading": {
          "type": "StructuredText",
          "config": {
            "label": "Heading",
            "placeholder": "",
            "allowTargetBlank": true,
            "multi": "heading3,strong,em"
          }
        },
        "description": {
          "type": "StructuredText",
          "config": {
            "label": "Description",
            "placeholder": "",
            "allowTargetBlank": true,
            "multi": "paragraph,strong,em,o-list-item,list-item"
          }
        }
      },
      "items": {}
    }
  ]
}